[
{"id": 1663694888947286018, "id_str": "1663694888947286018", "url": "https://twitter.com/smrtyboi/status/1663694888947286018", "date": "2023-05-30 23:52:26+00:00", "user": {"id": 1015762977885073408, "id_str": "1015762977885073408", "url": "https://twitter.com/smrtyboi", "username": "smrtyboi", "displayname": "pickle toes", "rawDescription": "my life is a meme", "created": "2018-07-08 01:02:20+00:00", "followersCount": 478, "friendsCount": 581, "statusesCount": 6116, "favouritesCount": 100564, "listedCount": 3, "mediaCount": 734, "location": "", "profileImageUrl": "https://pbs.twimg.com/profile_images/1543348343270739969/656Q2IVZ_normal.jpg", "profileBannerUrl": null, "protected": null, "verified": false, "blue": false, "blueType": null, "descriptionLinks": [], "_type": "snscrape.modules.twitter.User"}, "lang": "en", "rawContent": "@animalologist That roof has magical slutty properties", "replyCount": 1, "retweetCount": 0, "likeCount": 17, "quoteCount": 0, "conversationId": 1663694435757043713, "conversationIdStr": "1663694435757043713", "hashtags": [], "cashtags": [], "mentionedUsers": [{"id": 628565963, "id_str": "628565963", "username": "animalologist", "displayname": "taco belle", "_type": "snscrape.modules.twitter.UserRef"}], "links": [], "viewCount": 1186, "retweetedTweet": null, "quotedTweet": null, "place": null, "coordinates": null, "inReplyToTweetId": 1663694435757043713, "inReplyToTweetIdStr": "1663694435757043713", "inReplyToUser": {"id": 628565963, "id_str": "628565963", "username": "animalologist", "displayname": "taco belle", "_type": "snscrape.modules.twitter.UserRef"}, "source": "<a href=\"http://twitter.com/download/iphone\" rel=\"nofollow\">Twitter for iPhone</a>", "sourceUrl": "http://twitter.com/download/iphone", "sourceLabel": "Twitter for iPhone", "media": {"photos": [], "videos": [], "animated": []}, "_type": "snscrape.modules.twitter.Tweet"},
{"id": 1663693474523389952, "id_str": "1663693474523389952", "url": "https://twitter.com/sanandreafault/status/1663693474523389952", "date": "2023-05-30 23:46:48+00:00", "user": {"id": 216619614, "id_str": "216619614", "url": "https://twitter.com/sanandreafault", "username": "sanandreafault", "displayname": "The San Andreas Fault", "rawDescription": "I'm a faultline that runs through California. Lots of people fear me.", "created": "2010-11-17 07:45:03+00:00", "followersCount": 18168, "friendsCount": 90, "statusesCount": 5181, "favouritesCount": 679, "listedCount": 99, "mediaCount": 164, "location": "California", "profileImageUrl": "https://pbs.twimg.com/profile_images/1647902457/san-andreas-fault_normal.jpg", "profileBannerUrl": "https://pbs.twimg.com/profile_banners/216619614/1591077858", "protected": null, "verified": false, "blue": false, "blueType": null, "descriptionLinks": [], "_type": "snscrape.modules.twitter.User"}, "lang": "sv", "rawContent": "@MtStHelensWA Slut", "replyCount": 13, "retweetCount": 12, "likeCount": 350, "quoteCount": 4, "conversationId": 1663657805935693825, "conversationIdStr": "1663657805935693825", "hashtags": [], "cashtags": [], "mentionedUsers": [{"id": 781007071802163200, "id_str": "781007071802163200", "username": "MtStHelensWA", "displayname": "Mt. St. Helens", "_type": "snscrape.modules.twitter.UserRef"}], "links": [], "viewCount": 62445, "retweetedTweet": null, "quotedTweet": null, "place": null, "coordinates": null, "inReplyToTweetId": 1663657805935693825, "inReplyToTweetIdStr": "1663657805935693825", "inReplyToUser": {"id": 781007071802163200, "id_str": "781007071802163200", "username": "MtStHelensWA", "displayname": "Mt. St. Helens", "_type": "snscrape.modules.twitter.UserRef"}, "source": "<a href=\"http://twitter.com/download/iphone\" rel=\"nofollow\">Twitter for iPhone</a>", "sourceUrl": "http://twitter.com/download/iphone", "sourceLabel": "Twitter for iPhone", "media": {"photos": [], "videos": [], "animated": []}, "_type": "snscrape.modules.twitter.Tweet"},
{"id": 1663693256239071232, "id_str": "1663693256239071232", "url": "https://twitter.com/thinkerjackpot/status/1663693256239071232", "date": "2023-05-30 23:45:56+00:00", "user": {"id": 1436371049986379806, "id_str": "1436371049986379806", "url": "https://twitter.com/thinkerjackpot", "username": "thinkerjackpot", "displayname": "comfort for mj \ud83d\udcad", "rawDescription": "\u2014 the amazing spider-man #25 (june, 1965)", "created": "2021-09-10 16:48:46+00:00", "followersCount": 4017, "friendsCount": 253, "statusesCount": 2793, "favouritesCount": 11789, "listedCount": 16, "mediaCount": 1358, "location": "eng/pt-br", "profileImageUrl": "https://pbs.twimg.com/profile_images/1668800596428636160/_NXpTM-B_normal.jpg", "profileBannerUrl": "https://pbs.twimg.com/profile_banners/1436371049986379806/1631299712", "protected": null, "verified": false, "blue": false, "blueType": null, "descriptionLinks": [], "_type": "snscrape.modules.twitter.User"}, "lang": "en", "rawContent": "We're going to have *again* supposed \"spider-Man fans\" calling MJ a whore and other misogynistic slurs for the bad writing shes suffering. \nHonestly, I don't care much, cause they are all those losers w anime pf whose only function is to hate women on internet+ https://t.co/8xNFcI8yi4", "replyCount": 8, "retweetCount": 22, "likeCount": 164, "quoteCount": 1, "conversationId": 1663693256239071232, "conversationIdStr": "1663693256239071232", "hashtags": [], "cashtags": [], "mentionedUsers": [], "links": [], "viewCount": 6505, "retweetedTweet": null, "quotedTweet": null, "place": null, "coordinates": null, "inReplyToTweetId": null, "inReplyToTweetIdStr": null, "inReplyToUser": null, "source": "<a href=\"http://twitter.com/download/android\" rel=\"nofollow\">Twitter for Android</a>", "sourceUrl": "http://twitter.com/download/android", "sourceLabel": "Twitter for Android", "media": {"photos": [], "videos": [], "animated": [{"thumbnailUrl": "https://pbs.twimg.com/tweet_video_thumb/FxagMbWWwAIYSwH.jpg", "videoUrl": "https://video.twimg.com/tweet_video/FxagMbWWwAIYSwH.mp4"}]}, "_type": "snscrape.modules.twitter.Tweet"},
{"id": 1663693223049437186, "id_str": "1663693223049437186", "url": "https://twitter.com/worldofawfc/status/1663693223049437186", "date": "2023-05-30 23:45:48+00:00", "user": {"id": 1455265950668894218, "id_str": "1455265950668894218", "url": "https://twitter.com/worldofawfc", "username": "worldofawfc", "displayname": "sarah", "rawDescription": "arsenal", "created": "2021-11-01 20:10:27+00:00", "followersCount": 861, "friendsCount": 231, "statusesCount": 7292, "favouritesCount": 20200, "listedCount": 16, "mediaCount": 698, "location": "", "profileImageUrl": "https://pbs.twimg.com/profile_images/1521964658940391426/qHX1mYRD_normal.jpg", "profileBannerUrl": "https://pbs.twimg.com/profile_banners/1455265950668894218/1679541970", "protected": null, "verified": false, "blue": false, "blueType": null, "descriptionLinks": [], "_type": "snscrape.modules.twitter.User"}, "lang": "en", "rawContent": "I love being a whore \ud83d\ude0d touch grass", "replyCount": 2, "retweetCount": 0, "likeCount": 13, "quoteCount": 0, "conversationId": 1663693223049437186, "conversationIdStr": "1663693223049437186", "hashtags": [], "cashtags": [], "mentionedUsers": [], "links": [], "viewCount": 2018, "retweetedTweet": null, "quotedTweet": {"id": 1663685589760110593, "id_str": "1663685589760110593", "url": "https://twitter.com/Costryme/status/1663685589760110593", "date": "2023-05-30 23:15:29+00:00", "user": {"id": 729267248, "id_str": "729267248", "url": "https://twitter.com/Costryme", "username": "Costryme", "displayname": "Antoine", "rawDescription": "I happen to retweets things occasionally, and that's about it.", "created": "2012-07-31 21:19:37+00:00", "followersCount": 97, "friendsCount": 286, "statusesCount": 18045, "favouritesCount": 450, "listedCount": 2, "mediaCount": 558, "location": "Blowin' in the wind", "profileImageUrl": "https://pbs.twimg.com/profile_images/1540822184091942913/SYuv5piI_normal.jpg", "profileBannerUrl": "https://pbs.twimg.com/profile_banners/729267248/1421616669", "protected": null, "verified": false, "blue": false, "blueType": null, "descriptionLinks": [{"url": "http://www.antoinebeck.com", "text": "antoinebeck.com", "tcourl": "https://t.co/9XzYN2bVId"}], "_type": "snscrape.modules.twitter.User"}, "lang": "en", "rawContent": "@worldofawfc @memepatisserie Cool story, if you defend people calling refs whores, so are you !", "replyCount": 0, "retweetCount": 0, "likeCount": 0, "quoteCount": 2, "conversationId": 1663683993525694465, "conversationIdStr": "1663683993525694465", "hashtags": [], "cashtags": [], "mentionedUsers": [{"id": 1455265950668894218, "id_str": "1455265950668894218", "username": "worldofawfc", "displayname": "sarah", "_type": "snscrape.modules.twitter.UserRef"}], "links": [], "viewCount": 3640, "retweetedTweet": null, "quotedTweet": null, "place": null, "coordinates": null, "inReplyToTweetId": 1663685052515987459, "inReplyToTweetIdStr": "1663685052515987459", "inReplyToUser": {"id": 1455265950668894218, "id_str": "1455265950668894218", "username": "worldofawfc", "displayname": "sarah", "_type": "snscrape.modules.twitter.UserRef"}, "source": "<a href=\"http://twitter.com/download/iphone\" rel=\"nofollow\">Twitter for iPhone</a>", "sourceUrl": "http://twitter.com/download/iphone", "sourceLabel": "Twitter for iPhone", "media": {"photos": [], "videos": [], "animated": []}, "_type": "snscrape.modules.twitter.Tweet"}, "place": null, "coordinates": null, "inReplyToTweetId": null, "inReplyToTweetIdStr": null, "inReplyToUser": null, "source": "<a href=\"http://twitter.com/download/iphone\" rel=\"nofollow\">Twitter for iPhone</a>", "sourceUrl": "http://twitter.com/download/iphone", "sourceLabel": "Twitter for iPhone", "media": {"photos": [], "videos": [], "animated": []}, "_type": "snscrape.modules.twitter.Tweet"},
{"id": 1663685589760110593, "id_str": "1663685589760110593", "url": "https://twitter.com/Costryme/status/1663685589760110593", "date": "2023-05-30 23:15:29+00:00", "user": {"id": 729267248, "id_str": "729267248", "url": "https://twitter.com/Costryme", "username": "Costryme", "displayname": "Antoine", "rawDescription": "I happen to retweets things occasionally, and that's about it.", "created": "2012-07-31 21:19:37+00:00", "followersCount": 97, "friendsCount": 286, "statusesCount": 18045, "favouritesCount": 450, "listedCount": 2, "mediaCount": 558, "location": "Blowin' in the wind", "profileImageUrl": "https://pbs.twimg.com/profile_images/1540822184091942913/SYuv5piI_normal.jpg", "profileBannerUrl": "https://pbs.twimg.com/profile_banners/729267248/1421616669", "protected": null, "verified": false, "blue": false, "blueType": null, "descriptionLinks": [{"url": "http://www.antoinebeck.com", "text": "antoinebeck.com", "tcourl": "https://t.co/9XzYN2bVId"}], "_type": "snscrape.modules.twitter.User"}, "lang": "en", "rawContent": "@worldofawfc @memepatisserie Cool story, if you defend people calling refs whores, so are you !", "replyCount": 0, "retweetCount": 0, "likeCount": 0, "quoteCount": 2, "conversationId": 1663683993525694465, "conversationIdStr": "1663683993525694465", "hashtags": [], "cashtags": [], "mentionedUsers": [{"id": 1455265950668894218, "id_str": "1455265950668894218", "username": "worldofawfc", "displayname": "sarah", "_type": "snscrape.modules.twitter.UserRef"}], "links": [], "viewCount": 3640, "retweetedTweet": null, "quotedTweet": null, "place": null, "coordinates": null, "inReplyToTweetId": 1663685052515987459, "inReplyToTweetIdStr": "1663685052515987459", "inReplyToUser": {"id": 1455265950668894218, "id_str": "1455265950668894218", "username": "worldofawfc", "displayname": "sarah", "_type": "snscrape.modules.twitter.UserRef"}, "source": "<a href=\"http://twitter.com/download/iphone\" rel=\"nofollow\">Twitter for iPhone</a>", "sourceUrl": "http://twitter.com/download/iphone", "sourceLabel": "Twitter for iPhone", "media": {"photos": [], "videos": [], "animated": []}, "_type": "snscrape.modules.twitter.Tweet"},
{"id": 1663692244807720961, "id_str": "1663692244807720961", "url": "https://twitter.com/mgmoney50/status/1663692244807720961", "date": "2023-05-30 23:41:55+00:00", "user": {"id": 215296786, "id_str": "215296786", "url": "https://twitter.com/mgmoney50", "username": "mgmoney50", "displayname": "pcking23", "rawDescription": "Fate loves the fearless", "created": "2010-11-13 15:00:04+00:00", "followersCount": 371, "friendsCount": 93, "statusesCount": 8180, "favouritesCount": 764, "listedCount": 2, "mediaCount": 461, "location": "New York", "profileImageUrl": "https://pbs.twimg.com/profile_images/1684583728851431424/M8CXARfL_normal.jpg", "profileBannerUrl": "https://pbs.twimg.com/profile_banners/215296786/1690471212", "protected": null, "verified": false, "blue": false, "blueType": null, "descriptionLinks": [], "_type": "snscrape.modules.twitter.User"}, "lang": "en", "rawContent": "I dont think #allamerican realizes how crazy it looks for Jordan and Layla to be engaged. I can\u2019t get over it. She dated two of his groomsmen and was hooking with one of them again. I\u2019m not slut shaming her but even for a TV show your asking the fans for a lot. They are groomsmen", "replyCount": 2, "retweetCount": 7, "likeCount": 53, "quoteCount": 2, "conversationId": 1663692244807720961, "conversationIdStr": "1663692244807720961", "hashtags": ["allamerican"], "cashtags": [], "mentionedUsers": [], "links": [], "viewCount": 4474, "retweetedTweet": null, "quotedTweet": null, "place": null, "coordinates": null, "inReplyToTweetId": null, "inReplyToTweetIdStr": null, "inReplyToUser": null, "source": "<a href=\"http://twitter.com/download/iphone\" rel=\"nofollow\">Twitter for iPhone</a>", "sourceUrl": "http://twitter.com/download/iphone", "sourceLabel": "Twitter for iPhone", "media": {"photos": [], "videos": [], "animated": []}, "_type": "snscrape.modules.twitter.Tweet"},
{"id": 1663691441455919105, "id_str": "1663691441455919105", "url": "https://twitter.com/angelicwoman444/status/1663691441455919105", "date": "2023-05-30 23:38:44+00:00", "user": {"id": 1312104171550765057, "id_str": "1312104171550765057", "url": "https://twitter.com/angelicwoman444", "username": "angelicwoman444", "displayname": "aquarius baby", "rawDescription": "sent from heaven", "created": "2020-10-02 18:56:36+00:00", "followersCount": 10612, "friendsCount": 927, "statusesCount": 13582, "favouritesCount": 43343, "listedCount": 13, "mediaCount": 708, "location": "minors dni ", "profileImageUrl": "https://pbs.twimg.com/profile_images/1752090748009230336/P6Y2-rbH_normal.jpg", "profileBannerUrl": "https://pbs.twimg.com/profile_banners/1312104171550765057/1697599837", "protected": null, "verified": false, "blue": false, "blueType": null, "descriptionLinks": [{"url": "https://onlyfans.com/satanicwoman69", "text": "onlyfans.com/satanicwoman69", "tcourl": "https://t.co/HjE98yE5X2"}], "_type": "snscrape.modules.twitter.User"}, "lang": "en", "rawContent": "there are bitches i LOVE but would never let into my house like no hoe ur literally crazy but ily fr", "replyCount": 1, "retweetCount": 0, "likeCount": 22, "quoteCount": 0, "conversationId": 1663691441455919105, "conversationIdStr": "1663691441455919105", "hashtags": [], "cashtags": [], "mentionedUsers": [], "links": [], "viewCount": 1354, "retweetedTweet": null, "quotedTweet": null, "place": null, "coordinates": null, "inReplyToTweetId": null, "inReplyToTweetIdStr": null, "inReplyToUser": null, "source": "<a href=\"http://twitter.com/download/iphone\" rel=\"nofollow\">Twitter for iPhone</a>", "sourceUrl": "http://twitter.com/download/iphone", "sourceLabel": "Twitter for iPhone", "media": {"photos": [], "videos": [], "animated": []}, "_type": "snscrape.modules.twitter.Tweet"},
{"id": 1663689358317088769, "id_str": "1663689358317088769", "url": "https://twitter.com/summerahrens/status/1663689358317088769", "date": "2023-05-30 23:30:27+00:00", "user": {"id": 1191021820482400256, "id_str": "1191021820482400256", "url": "https://twitter.com/summerahrens", "username": "summerahrens", "displayname": "summer \u2661", "rawDescription": "angel, famous actress, model. NOT a national security threat. Luckiest Girl In The World. arial regular lover.\u2800 \u2800\u2800\u2800\u2800 \u2800\u2800\u2800\u2800\u2800\u2800\u2800\u2800 \u2800\u2800\u2800\u2800 \u2800 \u2800\u2800\u2800\u2800 \u2800\u2800", "created": "2019-11-03 15:58:35+00:00", "followersCount": 24960, "friendsCount": 1107, "statusesCount": 25300, "favouritesCount": 62551, "listedCount": 33, "mediaCount": 3892, "location": "behind you", "profileImageUrl": "https://pbs.twimg.com/profile_images/1625600380259164166/grwnzD40_normal.jpg", "profileBannerUrl": "https://pbs.twimg.com/profile_banners/1191021820482400256/1650088496", "protected": null, "verified": false, "blue": false, "blueType": null, "descriptionLinks": [{"url": "https://linktr.ee/summerdoes", "text": "linktr.ee/summerdoes", "tcourl": "https://t.co/czJBsAFJiY"}], "_type": "snscrape.modules.twitter.User"}, "lang": "en", "rawContent": "some of my moots are whores", "replyCount": 5, "retweetCount": 2, "likeCount": 67, "quoteCount": 1, "conversationId": 1663689358317088769, "conversationIdStr": "1663689358317088769", "hashtags": [], "cashtags": [], "mentionedUsers": [], "links": [], "viewCount": 4857, "retweetedTweet": null, "quotedTweet": null, "place": null, "coordinates": null, "inReplyToTweetId": null, "inReplyToTweetIdStr": null, "inReplyToUser": null, "source": "<a href=\"http://twitter.com/download/iphone\" rel=\"nofollow\">Twitter for iPhone</a>", "sourceUrl": "http://twitter.com/download/iphone", "sourceLabel": "Twitter for iPhone", "media": {"photos": [], "videos": [], "animated": []}, "_type": "snscrape.modules.twitter.Tweet"},
{"id": 1663689656846761989, "id_str": "1663689656846761989", "url": "https://twitter.com/oberynsgf/status/1663689656846761989", "date": "2023-05-30 23:31:38+00:00", "user": {"id": 2330580749, "id_str": "2330580749", "url": "https://twitter.com/oberynsgf", "username": "oberynsgf", "displayname": "marie (astarion\u2019s gf)", "rawDescription": "\u2014 in love with a world-endingly beautiful vampire. pedro pascal + adam driver enthusiast. \u22c6 fan account", "created": "2014-02-07 18:35:28+00:00", "followersCount": 3459, "friendsCount": 138, "statusesCount": 83111, "favouritesCount": 195808, "listedCount": 28, "mediaCount": 22212, "location": "they/them \u22c6 22 \u22c6 nb/bi \u22c6 nsfw", "profileImageUrl": "https://pbs.twimg.com/profile_images/1761561972280020992/sge6js9j_normal.jpg", "profileBannerUrl": "https://pbs.twimg.com/profile_banners/2330580749/1708824443", "protected": null, "verified": false, "blue": false, "blueType": null, "descriptionLinks": [], "_type": "snscrape.modules.twitter.User"}, "lang": "en", "rawContent": "he\u2019s such a hoe https://t.co/G0k9eJit5J", "replyCount": 0, "retweetCount": 22, "likeCount": 181, "quoteCount": 1, "conversationId": 1663689656846761989, "conversationIdStr": "1663689656846761989", "hashtags": [], "cashtags": [], "mentionedUsers": [], "links": [], "viewCount": 2764, "retweetedTweet": null, "quotedTweet": null, "place": null, "coordinates": null, "inReplyToTweetId": null, "inReplyToTweetIdStr": null, "inReplyToUser": null, "source": "<a href=\"http://twitter.com/download/iphone\" rel=\"nofollow\">Twitter for iPhone</a>", "sourceUrl": "http://twitter.com/download/iphone", "sourceLabel": "Twitter for iPhone", "media": {"photos": [], "videos": [], "animated": [{"thumbnailUrl": "https://pbs.twimg.com/tweet_video_thumb/Fxac5BSWYAIYOuq.jpg", "videoUrl": "https://video.twimg.com/tweet_video/Fxac5BSWYAIYOuq.mp4"}]}, "_type": "snscrape.modules.twitter.Tweet"},
{"id": 1663688989335846914, "id_str": "1663688989335846914", "url": "https://twitter.com/softestauraa/status/1663688989335846914", "date": "2023-05-30 23:28:59+00:00", "user": {"id": 1651717493033934848, "id_str": "1651717493033934848", "url": "https://twitter.com/softestauraa", "username": "softestauraa", "displayname": "lexi\ufe0e \ufe0e \u0b68\u0b67", "rawDescription": "alemeda noticed x2", "created": "2023-04-27 22:38:55+00:00", "followersCount": 3080, "friendsCount": 2997, "statusesCount": 5138, "favouritesCount": 18078, "listedCount": 1, "mediaCount": 624, "location": "sza and summer noticed .", "profileImageUrl": "https://pbs.twimg.com/profile_images/1765904382468472832/rajLQ2X7_normal.jpg", "profileBannerUrl": "https://pbs.twimg.com/profile_banners/1651717493033934848/1709859399", "protected": null, "verified": false, "blue": false, "blueType": null, "descriptionLinks": [{"url": "https://www.gofundme.com/f/help-evacuate-haythams-family-out-of-gaza-war", "text": "gofundme.com/f/help-evacuat\u2026", "tcourl": "https://t.co/QjobCXOZjV"}], "_type": "snscrape.modules.twitter.User"}, "lang": "en", "rawContent": "\u201cit\u2019s either bro\u2019d out or hoe\u2019d out no in between. \u201c https://t.co/7jYjub3jv0", "replyCount": 1, "retweetCount": 1, "likeCount": 23, "quoteCount": 0, "conversationId": 1663688989335846914, "conversationIdStr": "1663688989335846914", "hashtags": [], "cashtags": [], "mentionedUsers": [], "links": [], "viewCount": 676, "retweetedTweet": null, "quotedTweet": null, "place": null, "coordinates": null, "inReplyToTweetId": null, "inReplyToTweetIdStr": null, "inReplyToUser": null, "source": "<a href=\"http://twitter.com/download/iphone\" rel=\"nofollow\">Twitter for iPhone</a>", "sourceUrl": "http://twitter.com/download/iphone", "sourceLabel": "Twitter for iPhone", "media": {"photos": [{"url": "https://pbs.twimg.com/media/FxacT8EXgAIwUJK.jpg"}, {"url": "https://pbs.twimg.com/media/FxacT8BWcAIpgNB.jpg"}, {"url": "https://pbs.twimg.com/media/FxacT8BWwA48s51.jpg"}, {"url": "https://pbs.twimg.com/media/FxacT8BWIAAp9SI.jpg"}], "videos": [], "animated": []}, "_type": "snscrape.modules.twitter.Tweet"},
{"id": 1663688881714130947, "id_str": "1663688881714130947", "url": "https://twitter.com/coolaidhehe/status/1663688881714130947", "date": "2023-05-30 23:28:33+00:00", "user": {"id": 1265584509778571264, "id_str": "1265584509778571264", "url": "https://twitter.com/coolaidhehe", "username": "coolaidhehe", "displayname": "ahhhhh", "rawDescription": "New to thiss", "created": "2020-05-27 10:04:02+00:00", "followersCount": 32, "friendsCount": 12, "statusesCount": 6752, "favouritesCount": 26556, "listedCount": 0, "mediaCount": 1110, "location": "", "profileImageUrl": "https://pbs.twimg.com/profile_images/1423028833880616963/ibVTcI64_normal.jpg", "profileBannerUrl": "https://pbs.twimg.com/profile_banners/1265584509778571264/1628111489", "protected": null, "verified": false, "blue": false, "blueType": null, "descriptionLinks": [], "_type": "snscrape.modules.twitter.User"}, "lang": "en", "rawContent": "@residual7income @hiamandag @lyemcfly If dating = whore then yep!", "replyCount": 1, "retweetCount": 0, "likeCount": 29, "quoteCount": 0, "conversationId": 1663527698436612097, "conversationIdStr": "1663527698436612097", "hashtags": [], "cashtags": [], "mentionedUsers": [{"id": 4174939725, "id_str": "4174939725", "username": "residual7income", "displayname": "6", "_type": "snscrape.modules.twitter.UserRef"}, {"id": 1212541429609713665, "id_str": "1212541429609713665", "username": "hiamandag", "displayname": "\u043c\u0455. \u03b1\u043c\u03b1\u03b7\u2202\u03b1", "_type": "snscrape.modules.twitter.UserRef"}, {"id": 30265388, "id_str": "30265388", "username": "lyemcfly", "displayname": "888 \ud83d\udc09", "_type": "snscrape.modules.twitter.UserRef"}], "links": [], "viewCount": 761, "retweetedTweet": null, "quotedTweet": null, "place": null, "coordinates": null, "inReplyToTweetId": 1663672964707938306, "inReplyToTweetIdStr": "1663672964707938306", "inReplyToUser": {"id": 4174939725, "id_str": "4174939725", "username": "residual7income", "displayname": "6", "_type": "snscrape.modules.twitter.UserRef"}, "source": "<a href=\"http://twitter.com/download/iphone\" rel=\"nofollow\">Twitter for iPhone</a>", "sourceUrl": "http://twitter.com/download/iphone", "sourceLabel": "Twitter for iPhone", "media": {"photos": [], "videos": [], "animated": []}, "_type": "snscrape.modules.twitter.Tweet"},
{"id": 1663688502180040706, "id_str": "1663688502180040706", "url": "https://twitter.com/coastal_hoe/status/1663688502180040706", "date": "2023-05-30 23:27:03+00:00", "user": {"id": 949731699084218369, "id_str": "949731699084218369", "url": "https://twitter.com/coastal_hoe", "username": "coastal_hoe", "displayname": "Tyler", "rawDescription": "28 | \ud83c\udff3\ufe0f\u200d\ud83c\udf08 | New England | insta: anchorsagay", "created": "2018-01-06 19:57:37+00:00", "followersCount": 26632, "friendsCount": 2309, "statusesCount": 15367, "favouritesCount": 99618, "listedCount": 18, "mediaCount": 855, "location": "Connecticut, USA", "profileImageUrl": "https://pbs.twimg.com/profile_images/1703384483112570880/7s8-Iryi_normal.jpg", "profileBannerUrl": "https://pbs.twimg.com/profile_banners/949731699084218369/1608775434", "protected": null, "verified": false, "blue": false, "blueType": null, "descriptionLinks": [], "_type": "snscrape.modules.twitter.User"}, "lang": "en", "rawContent": "It\u2019s literally just gone https://t.co/lgkN5cjf5j", "replyCount": 3, "retweetCount": 0, "likeCount": 27, "quoteCount": 0, "conversationId": 1663688502180040706, "conversationIdStr": "1663688502180040706", "hashtags": [], "cashtags": [], "mentionedUsers": [], "links": [], "viewCount": 10393, "retweetedTweet": null, "quotedTweet": {"id": 1663679537425645570, "id_str": "1663679537425645570", "url": "https://twitter.com/coastal_hoe/status/1663679537425645570", "date": "2023-05-30 22:51:26+00:00", "user": {"id": 949731699084218369, "id_str": "949731699084218369", "url": "https://twitter.com/coastal_hoe", "username": "coastal_hoe", "displayname": "Tyler", "rawDescription": "28 | \ud83c\udff3\ufe0f\u200d\ud83c\udf08 | New England | insta: anchorsagay", "created": "2018-01-06 19:57:37+00:00", "followersCount": 26632, "friendsCount": 2309, "statusesCount": 15367, "favouritesCount": 99618, "listedCount": 18, "mediaCount": 855, "location": "Connecticut, USA", "profileImageUrl": "https://pbs.twimg.com/profile_images/1703384483112570880/7s8-Iryi_normal.jpg", "profileBannerUrl": "https://pbs.twimg.com/profile_banners/949731699084218369/1608775434", "protected": null, "verified": false, "blue": false, "blueType": null, "descriptionLinks": [], "_type": "snscrape.modules.twitter.User"}, "lang": "en", "rawContent": "Where the fuck did my notifications go", "replyCount": 0, "retweetCount": 0, "likeCount": 11, "quoteCount": 1, "conversationId": 1663679537425645570, "conversationIdStr": "1663679537425645570", "hashtags": [], "cashtags": [], "mentionedUsers": [], "links": [], "viewCount": 11586, "retweetedTweet": null, "quotedTweet": null, "place": null, "coordinates": null, "inReplyToTweetId": null, "inReplyToTweetIdStr": null, "inReplyToUser": null, "source": "<a href=\"http://twitter.com/download/iphone\" rel=\"nofollow\">Twitter for iPhone</a>", "sourceUrl": "http://twitter.com/download/iphone", "sourceLabel": "Twitter for iPhone", "media": {"photos": [], "videos": [], "animated": []}, "_type": "snscrape.modules.twitter.Tweet"}, "place": null, "coordinates": null, "inReplyToTweetId": null, "inReplyToTweetIdStr": null, "inReplyToUser": null, "source": "<a href=\"http://twitter.com/download/iphone\" rel=\"nofollow\">Twitter for iPhone</a>", "sourceUrl": "http://twitter.com/download/iphone", "sourceLabel": "Twitter for iPhone", "media": {"photos": [{"url": "https://pbs.twimg.com/media/Fxab4BZXgAAPOFy.jpg"}], "videos": [], "animated": []}, "_type": "snscrape.modules.twitter.Tweet"},
{"id": 1663679537425645570, "id_str": "1663679537425645570", "url": "https://twitter.com/coastal_hoe/status/1663679537425645570", "date": "2023-05-30 22:51:26+00:00", "user": {"id": 949731699084218369, "id_str": "949731699084218369", "url": "https://twitter.com/coastal_hoe", "username": "coastal_hoe", "displayname": "Tyler", "rawDescription": "28 | \ud83c\udff3\ufe0f\u200d\ud83c\udf08 | New England | insta: anchorsagay", "created": "2018-01-06 19:57:37+00:00", "followersCount": 26632, "friendsCount": 2309, "statusesCount": 15367, "favouritesCount": 99618, "listedCount": 18, "mediaCount": 855, "location": "Connecticut, USA", "profileImageUrl": "https://pbs.twimg.com/profile_images/1703384483112570880/7s8-Iryi_normal.jpg", "profileBannerUrl": "https://pbs.twimg.com/profile_banners/949731699084218369/1608775434", "protected": null, "verified": false, "blue": false, "blueType": null, "descriptionLinks": [], "_type": "snscrape.modules.twitter.User"}, "lang": "en", "rawContent": "Where the fuck did my notifications go", "replyCount": 0, "retweetCount": 0, "likeCount": 11, "quoteCount": 1, "conversationId": 1663679537425645570, "conversationIdStr": "1663679537425645570", "hashtags": [], "cashtags": [], "mentionedUsers": [], "links": [], "viewCount": 11586, "retweetedTweet": null, "quotedTweet": null, "place": null, "coordinates": null, "inReplyToTweetId": null, "inReplyToTweetIdStr": null, "inReplyToUser": null, "source": "<a href=\"http://twitter.com/download/iphone\" rel=\"nofollow\">Twitter for iPhone</a>", "sourceUrl": "http://twitter.com/download/iphone", "sourceLabel": "Twitter for iPhone", "media": {"photos": [], "videos": [], "animated": []}, "_type": "snscrape.modules.twitter.Tweet"},
{"id": 1663687021485801473, "id_str": "1663687021485801473", "url": "https://twitter.com/lmp3rfect/status/1663687021485801473", "date": "2023-05-30 23:21:10+00:00", "user": {"id": 1254218638128791552, "id_str": "1254218638128791552", "url": "https://twitter.com/lmp3rfect", "username": "lmp3rfect", "displayname": "by \ud83d\udd3b", "rawDescription": "I\u2019m perfect.  ig: byr69n", "created": "2020-04-26 01:20:05+00:00", "followersCount": 16372, "friendsCount": 1141, "statusesCount": 93970, "favouritesCount": 119250, "listedCount": 35, "mediaCount": 9592, "location": "  theythem", "profileImageUrl": "https://pbs.twimg.com/profile_images/1763265418465042432/IT4LHJpn_normal.jpg", "profileBannerUrl": "https://pbs.twimg.com/profile_banners/1254218638128791552/1709932457", "protected": null, "verified": false, "blue": false, "blueType": null, "descriptionLinks": [{"url": "http://linktree.com/byrunt", "text": "linktree.com/byrunt", "tcourl": "https://t.co/3k20cqKJeP"}], "_type": "snscrape.modules.twitter.User"}, "lang": "en", "rawContent": "Will never forget how I was hooking up and he hit me in my stomach and I literally made him stop because who the fuck raised you", "replyCount": 1, "retweetCount": 1, "likeCount": 49, "quoteCount": 0, "conversationId": 1663686885766561792, "conversationIdStr": "1663686885766561792", "hashtags": [], "cashtags": [], "mentionedUsers": [], "links": [], "viewCount": 2024, "retweetedTweet": null, "quotedTweet": null, "place": null, "coordinates": null, "inReplyToTweetId": 1663686885766561792, "inReplyToTweetIdStr": "1663686885766561792", "inReplyToUser": {"id": 1254218638128791552, "id_str": "1254218638128791552", "username": "lmp3rfect", "displayname": "by \ud83d\udd3b", "_type": "snscrape.modules.twitter.UserRef"}, "source": "<a href=\"http://twitter.com/#!/download/ipad\" rel=\"nofollow\">Twitter for iPad</a>", "sourceUrl": "http://twitter.com/#!/download/ipad", "sourceLabel": "Twitter for iPad", "media": {"photos": [], "videos": [], "animated": []}, "_type": "snscrape.modules.twitter.Tweet"},
{"id": 1663686422958600192, "id_str": "1663686422958600192", "url": "https://twitter.com/atg_curry/status/1663686422958600192", "date": "2023-05-30 23:18:47+00:00", "user": {"id": 1486036736769728514, "id_str": "1486036736769728514", "url": "https://twitter.com/atg_curry", "username": "atg_curry", "displayname": "ATG Curry", "rawDescription": "Artist. N.ever F.orget L.oyalty \u267f\ufe0f IG: atg.curry DM for promo!", "created": "2022-01-25 18:02:46+00:00", "followersCount": 5922, "friendsCount": 5438, "statusesCount": 28124, "favouritesCount": 28481, "listedCount": 1, "mediaCount": 172, "location": "Atlanta, GA", "profileImageUrl": "https://pbs.twimg.com/profile_images/1745574967335415808/hAM4WZHt_normal.jpg", "profileBannerUrl": "https://pbs.twimg.com/profile_banners/1486036736769728514/1705809595", "protected": null, "verified": false, "blue": true, "blueType": null, "descriptionLinks": [{"url": "https://music.apple.com/us/album/dikmatized/1645936148?i=1645936149", "text": "music.apple.com/us/album/dikma\u2026", "tcourl": "https://t.co/xkzvLF6VhH"}], "_type": "snscrape.modules.twitter.User"}, "lang": "en", "rawContent": "Y\u2019all love blaming y\u2019all zodiac signs \u201cima asparagus\u201d no you a HOE \ud83e\udd23", "replyCount": 1, "retweetCount": 41, "likeCount": 66, "quoteCount": 9, "conversationId": 1663686422958600192, "conversationIdStr": "1663686422958600192", "hashtags": [], "cashtags": [], "mentionedUsers": [], "links": [], "viewCount": 6496, "retweetedTweet": null, "quotedTweet": null, "place": null, "coordinates": null, "inReplyToTweetId": null, "inReplyToTweetIdStr": null, "inReplyToUser": null, "source": "<a href=\"http://twitter.com/download/iphone\" rel=\"nofollow\">Twitter for iPhone</a>", "sourceUrl": "http://twitter.com/download/iphone", "sourceLabel": "Twitter for iPhone", "media": {"photos": [], "videos": [], "animated": []}, "_type": "snscrape.modules.twitter.Tweet"},
{"id": 1663685833185017858, "id_str": "1663685833185017858", "url": "https://twitter.com/savagexmoods_/status/1663685833185017858", "date": "2023-05-30 23:16:27+00:00", "user": {"id": 1155172874539458560, "id_str": "1155172874539458560", "url": "https://twitter.com/savagexmoods_", "username": "savagexmoods_", "displayname": "\ud835\udce8\ud835\udcf8\ud835\udcf7\ud835\udcea\ud835\udcf1 \ud83e\udd40", "rawDescription": "\u273fYonah | \u201cPlain and simple treat her like a pimple this bitch gettin popped\u201d", "created": "2019-07-27 17:47:30+00:00", "followersCount": 402, "friendsCount": 162, "statusesCount": 10343, "favouritesCount": 18267, "listedCount": 0, "mediaCount": 4596, "location": "GAG CITY", "profileImageUrl": "https://pbs.twimg.com/profile_images/1760503275932061696/M9hxgCpS_normal.jpg", "profileBannerUrl": "https://pbs.twimg.com/profile_banners/1155172874539458560/1709034667", "protected": null, "verified": false, "blue": false, "blueType": null, "descriptionLinks": [], "_type": "snscrape.modules.twitter.User"}, "lang": "en", "rawContent": "Like ok?? Y'all fav slept with 20 different women within a month after his divorce while still calling L**** a whore and still got in her pants too \ud83e\udd23\ud83e\udd23 https://t.co/UYihmygV5m", "replyCount": 2, "retweetCount": 3, "likeCount": 28, "quoteCount": 1, "conversationId": 1663685833185017858, "conversationIdStr": "1663685833185017858", "hashtags": [], "cashtags": [], "mentionedUsers": [], "links": [], "viewCount": 2469, "retweetedTweet": null, "quotedTweet": {"id": 1663684369670631463, "id_str": "1663684369670631463", "url": "https://twitter.com/GagnerStar/status/1663684369670631463", "date": "2023-05-30 23:10:38+00:00", "user": {"id": 168040804, "id_str": "168040804", "url": "https://twitter.com/GagnerStar", "username": "GagnerStar", "displayname": "A *hiatus*", "rawDescription": "Middle of Nowhere|fanaccount|", "created": "2010-07-18 06:16:56+00:00", "followersCount": 1369, "friendsCount": 424, "statusesCount": 56459, "favouritesCount": 80019, "listedCount": 8, "mediaCount": 1889, "location": "", "profileImageUrl": "https://pbs.twimg.com/profile_images/1662243234557337604/Y8tofHI1_normal.jpg", "profileBannerUrl": "https://pbs.twimg.com/profile_banners/168040804/1632900129", "protected": null, "verified": false, "blue": false, "blueType": null, "descriptionLinks": [], "_type": "snscrape.modules.twitter.User"}, "lang": "en", "rawContent": "Alicia is not a gotcha. She won\u2019t ever be. Y\u2019all looking at the bottom of the barrel to find something. https://t.co/z695oW1foN", "replyCount": 1, "retweetCount": 6, "likeCount": 38, "quoteCount": 2, "conversationId": 1663684369670631463, "conversationIdStr": "1663684369670631463", "hashtags": [], "cashtags": [], "mentionedUsers": [], "links": [], "viewCount": 3809, "retweetedTweet": null, "quotedTweet": null, "place": null, "coordinates": null, "inReplyToTweetId": null, "inReplyToTweetIdStr": null, "inReplyToUser": null, "source": "<a href=\"http://twitter.com/download/iphone\" rel=\"nofollow\">Twitter for iPhone</a>", "sourceUrl": "http://twitter.com/download/iphone", "sourceLabel": "Twitter for iPhone", "media": {"photos": [], "videos": [], "animated": [{"thumbnailUrl": "https://pbs.twimg.com/tweet_video_thumb/FxaYHSOX0AAYBj3.jpg", "videoUrl": "https://video.twimg.com/tweet_video/FxaYHSOX0AAYBj3.mp4"}]}, "_type": "snscrape.modules.twitter.Tweet"}, "place": null, "coordinates": null, "inReplyToTweetId": null, "inReplyToTweetIdStr": null, "inReplyToUser": null, "source": "<a href=\"http://twitter.com/download/iphone\" rel=\"nofollow\">Twitter for iPhone</a>", "sourceUrl": "http://twitter.com/download/iphone", "sourceLabel": "Twitter for iPhone", "media": {"photos": [], "videos": [], "animated": [{"thumbnailUrl": "https://pbs.twimg.com/tweet_video_thumb/FxaZcb2XwAEfVsm.jpg", "videoUrl": "https://video.twimg.com/tweet_video/FxaZcb2XwAEfVsm.mp4"}]}, "_type": "snscrape.modules.twitter.Tweet"},
{"id": 1663684369670631463, "id_str": "1663684369670631463", "url": "https://twitter.com/GagnerStar/status/1663684369670631463", "date": "2023-05-30 23:10:38+00:00", "user": {"id": 168040804, "id_str": "168040804", "url": "https://twitter.com/GagnerStar", "username": "GagnerStar", "displayname": "A *hiatus*", "rawDescription": "Middle of Nowhere|fanaccount|", "created": "2010-07-18 06:16:56+00:00", "followersCount": 1369, "friendsCount": 424, "statusesCount": 56459, "favouritesCount": 80019, "listedCount": 8, "mediaCount": 1889, "location": "", "profileImageUrl": "https://pbs.twimg.com/profile_images/1662243234557337604/Y8tofHI1_normal.jpg", "profileBannerUrl": "https://pbs.twimg.com/profile_banners/168040804/1632900129", "protected": null, "verified": false, "blue": false, "blueType": null, "descriptionLinks": [], "_type": "snscrape.modules.twitter.User"}, "lang": "en", "rawContent": "Alicia is not a gotcha. She won\u2019t ever be. Y\u2019all looking at the bottom of the barrel to find something. https://t.co/z695oW1foN", "replyCount": 1, "retweetCount": 6, "likeCount": 38, "quoteCount": 2, "conversationId": 1663684369670631463, "conversationIdStr": "1663684369670631463", "hashtags": [], "cashtags": [], "mentionedUsers": [], "links": [], "viewCount": 3809, "retweetedTweet": null, "quotedTweet": null, "place": null, "coordinates": null, "inReplyToTweetId": null, "inReplyToTweetIdStr": null, "inReplyToUser": null, "source": "<a href=\"http://twitter.com/download/iphone\" rel=\"nofollow\">Twitter for iPhone</a>", "sourceUrl": "http://twitter.com/download/iphone", "sourceLabel": "Twitter for iPhone", "media": {"photos": [], "videos": [], "animated": [{"thumbnailUrl": "https://pbs.twimg.com/tweet_video_thumb/FxaYHSOX0AAYBj3.jpg", "videoUrl": "https://video.twimg.com/tweet_video/FxaYHSOX0AAYBj3.mp4"}]}, "_type": "snscrape.modules.twitter.Tweet"},
{"id": 1663685132610412549, "id_str": "1663685132610412549", "url": "https://twitter.com/citynightcap/status/1663685132610412549", "date": "2023-05-30 23:13:40+00:00", "user": {"id": 17524394, "id_str": "17524394", "url": "https://twitter.com/citynightcap", "username": "citynightcap", "displayname": "Robert Davenport, Tanky \ud83c\udff4\ud83c\udf49", "rawDescription": "Dead fake 17th C dramatist-once famous &successful now forgotten. I read. No TV. No Uber. I delete. I make you think-you wont like it. I ALWAYS VOTE D.", "created": "2008-11-20 22:27:19+00:00", "followersCount": 18641, "friendsCount": 17617, "statusesCount": 49779, "favouritesCount": 332686, "listedCount": 12, "mediaCount": 222, "location": "Dead per bio, buried Deptford", "profileImageUrl": "https://pbs.twimg.com/profile_images/822505509014093824/uN5fFrqy_normal.jpg", "profileBannerUrl": "https://pbs.twimg.com/profile_banners/17524394/1647285658", "protected": null, "verified": false, "blue": false, "blueType": null, "descriptionLinks": [], "_type": "snscrape.modules.twitter.User"}, "lang": "en", "rawContent": "So it\u2019s #believewomen and #metoo until it\u2019s a 60 year old highly educated former US Senate staffer forced to flee for her life. Then she\u2019s a heifer, a slut, a pig, an op, a trayter. \n\nHow can you people even live with yourselves?", "replyCount": 6, "retweetCount": 4, "likeCount": 21, "quoteCount": 1, "conversationId": 1663685132610412549, "conversationIdStr": "1663685132610412549", "hashtags": ["believewomen", "metoo"], "cashtags": [], "mentionedUsers": [], "links": [], "viewCount": 726, "retweetedTweet": null, "quotedTweet": null, "place": null, "coordinates": null, "inReplyToTweetId": null, "inReplyToTweetIdStr": null, "inReplyToUser": null, "source": "<a href=\"http://twitter.com/download/iphone\" rel=\"nofollow\">Twitter for iPhone</a>", "sourceUrl": "http://twitter.com/download/iphone", "sourceLabel": "Twitter for iPhone", "media": {"photos": [], "videos": [], "animated": []}, "_type": "snscrape.modules.twitter.Tweet"},
{"id": 1663684982236233730, "id_str": "1663684982236233730", "url": "https://twitter.com/Florencebabyxxx/status/1663684982236233730", "date": "2023-05-30 23:13:04+00:00", "user": {"id": 1285823663871111169, "id_str": "1285823663871111169", "url": "https://twitter.com/Florencebabyxxx", "username": "Florencebabyxxx", "displayname": "Flo", "rawDescription": "bark bark bark", "created": "2020-07-22 06:28:04+00:00", "followersCount": 109, "friendsCount": 424, "statusesCount": 11998, "favouritesCount": 134478, "listedCount": 4, "mediaCount": 615, "location": "Canadaland ", "profileImageUrl": "https://pbs.twimg.com/profile_images/1319686567653302272/am3GMQmI_normal.jpg", "profileBannerUrl": "https://pbs.twimg.com/profile_banners/1285823663871111169/1615603928", "protected": null, "verified": false, "blue": false, "blueType": null, "descriptionLinks": [], "_type": "snscrape.modules.twitter.User"}, "lang": "en", "rawContent": "@NinjaGrandma5 @shelly2161 @KWHUBIS @LifeNewsToo They literally scream at women calling us whores and the devil and worse while we are going through the most horrible decisions of our life. They literally try to stop you from going in to a medical appointment that is NONE OF THERE FUCKING BUSINESS. that is terrorism.", "replyCount": 3, "retweetCount": 0, "likeCount": 61, "quoteCount": 0, "conversationId": 1662932010019553283, "conversationIdStr": "1662932010019553283", "hashtags": [], "cashtags": [], "mentionedUsers": [{"id": 1483454849547186186, "id_str": "1483454849547186186", "username": "NinjaGrandma5", "displayname": "Ninja Grandma", "_type": "snscrape.modules.twitter.UserRef"}, {"id": 3050411297, "id_str": "3050411297", "username": "shelly2161", "displayname": "shelly - MCV-research / CATS Initiative", "_type": "snscrape.modules.twitter.UserRef"}, {"id": 1519327477050449920, "id_str": "1519327477050449920", "username": "KWHUBIS", "displayname": "Ken Hubbard", "_type": "snscrape.modules.twitter.UserRef"}, {"id": 74552263, "id_str": "74552263", "username": "LifeNewsToo", "displayname": "Stop Abortion Now", "_type": "snscrape.modules.twitter.UserRef"}], "links": [], "viewCount": 699, "retweetedTweet": null, "quotedTweet": null, "place": null, "coordinates": null, "inReplyToTweetId": 1663280129072676864, "inReplyToTweetIdStr": "1663280129072676864", "inReplyToUser": {"id": 1483454849547186186, "id_str": "1483454849547186186", "username": "NinjaGrandma5", "displayname": "Ninja Grandma", "_type": "snscrape.modules.twitter.UserRef"}, "source": "<a href=\"http://twitter.com/download/iphone\" rel=\"nofollow\">Twitter for iPhone</a>", "sourceUrl": "http://twitter.com/download/iphone", "sourceLabel": "Twitter for iPhone", "media": {"photos": [], "videos": [], "animated": []}, "_type": "snscrape.modules.twitter.Tweet"},
{"id": 1663683793113300992, "id_str": "1663683793113300992", "url": "https://twitter.com/brwngrlkaren/status/1663683793113300992", "date": "2023-05-30 23:08:20+00:00", "user": {"id": 2366269672, "id_str": "2366269672", "url": "https://twitter.com/brwngrlkaren", "username": "brwngrlkaren", "displayname": "the king", "rawDescription": "(NOT) simulated brown girl", "created": "2014-02-26 04:33:30+00:00", "followersCount": 1469, "friendsCount": 621, "statusesCount": 252089, "favouritesCount": 729618, "listedCount": 7, "mediaCount": 1279, "location": "$30 DM fee $100 UNBLOCKING fee", "profileImageUrl": "https://pbs.twimg.com/profile_images/1731764648943194112/YsOaChtJ_normal.jpg", "profileBannerUrl": "https://pbs.twimg.com/profile_banners/2366269672/1709307786", "protected": null, "verified": false, "blue": false, "blueType": null, "descriptionLinks": [], "_type": "snscrape.modules.twitter.User"}, "lang": "en", "rawContent": "@jacksaint101 you lying in the replies and calling US whores??? https://t.co/5Vj3KJOAIN", "replyCount": 4, "retweetCount": 4, "likeCount": 236, "quoteCount": 0, "conversationId": 1663549488995393537, "conversationIdStr": "1663549488995393537", "hashtags": [], "cashtags": [], "mentionedUsers": [{"id": 2539717229, "id_str": "2539717229", "username": "jacksaint101", "displayname": "J_og", "_type": "snscrape.modules.twitter.UserRef"}], "links": [], "viewCount": 4960, "retweetedTweet": null, "quotedTweet": null, "place": null, "coordinates": null, "inReplyToTweetId": 1663659589613543426, "inReplyToTweetIdStr": "1663659589613543426", "inReplyToUser": {"id": 2539717229, "id_str": "2539717229", "username": "jacksaint101", "displayname": "J_og", "_type": "snscrape.modules.twitter.UserRef"}, "source": "<a href=\"http://twitter.com/download/iphone\" rel=\"nofollow\">Twitter for iPhone</a>", "sourceUrl": "http://twitter.com/download/iphone", "sourceLabel": "Twitter for iPhone", "media": {"photos": [], "videos": [], "animated": [{"thumbnailUrl": "https://pbs.twimg.com/tweet_video_thumb/FxaXlhsWAAIqDUB.jpg", "videoUrl": "https://video.twimg.com/tweet_video/FxaXlhsWAAIqDUB.mp4"}]}, "_type": "snscrape.modules.twitter.Tweet"},
{"id": 1663683722502340608, "id_str": "1663683722502340608", "url": "https://twitter.com/balladofcaius/status/1663683722502340608", "date": "2023-05-30 23:08:03+00:00", "user": {"id": 842536844894134272, "id_str": "842536844894134272", "url": "https://twitter.com/balladofcaius", "username": "balladofcaius", "displayname": "BalladOfCaius \ud83c\udff3\ufe0f\u200d\ud83c\udf08", "rawDescription": "Seth | he/him | Gay as Fuck | Black Trans Lives Matter | Sex Work is Real Work", "created": "2017-03-17 00:43:32+00:00", "followersCount": 1638, "friendsCount": 1498, "statusesCount": 22724, "favouritesCount": 104363, "listedCount": 7, "mediaCount": 2612, "location": "San Francisco, CA", "profileImageUrl": "https://pbs.twimg.com/profile_images/1664716310771798028/ma1HJZhW_normal.jpg", "profileBannerUrl": "https://pbs.twimg.com/profile_banners/842536844894134272/1640792803", "protected": null, "verified": false, "blue": false, "blueType": null, "descriptionLinks": [], "_type": "snscrape.modules.twitter.User"}, "lang": "en", "rawContent": "@OhHeyDJ For some reason this post is getting attention so I shall shamelessly attach this post gym thirst trap I just took \n\nUs thicc bitches can turn the party and slut it up too! https://t.co/XvPvZ2A0a2", "replyCount": 4, "retweetCount": 2, "likeCount": 77, "quoteCount": 0, "conversationId": 1663630195457421312, "conversationIdStr": "1663630195457421312", "hashtags": [], "cashtags": [], "mentionedUsers": [{"id": 15164892, "id_str": "15164892", "username": "OhHeyDJ", "displayname": "D.J. Kirkland", "_type": "snscrape.modules.twitter.UserRef"}], "links": [], "viewCount": 1495, "retweetedTweet": null, "quotedTweet": null, "place": null, "coordinates": null, "inReplyToTweetId": 1663630195457421312, "inReplyToTweetIdStr": "1663630195457421312", "inReplyToUser": {"id": 842536844894134272, "id_str": "842536844894134272", "username": "balladofcaius", "displayname": "BalladOfCaius \ud83c\udff3\ufe0f\u200d\ud83c\udf08", "_type": "snscrape.modules.twitter.UserRef"}, "source": "<a href=\"http://twitter.com/download/android\" rel=\"nofollow\">Twitter for Android</a>", "sourceUrl": "http://twitter.com/download/android", "sourceLabel": "Twitter for Android", "media": {"photos": [{"url": "https://pbs.twimg.com/media/FxaXh3LaUAAjY--.jpg"}], "videos": [], "animated": []}, "_type": "snscrape.modules.twitter.Tweet"},
{"id": 1663683269299408896, "id_str": "1663683269299408896", "url": "https://twitter.com/josielizond/status/1663683269299408896", "date": "2023-05-30 23:06:15+00:00", "user": {"id": 870143649731928064, "id_str": "870143649731928064", "url": "https://twitter.com/josielizond", "username": "josielizond", "displayname": "joc \u26a2", "rawDescription": "20. virgo. \ud83c\udf08\ud83e\uddda\u200d\u2640\ufe0f", "created": "2017-06-01 05:03:07+00:00", "followersCount": 1085, "friendsCount": 628, "statusesCount": 6524, "favouritesCount": 18878, "listedCount": 0, "mediaCount": 84, "location": "", "profileImageUrl": "https://pbs.twimg.com/profile_images/1734052871929466880/U8xr5VH5_normal.jpg", "profileBannerUrl": "https://pbs.twimg.com/profile_banners/870143649731928064/1709796742", "protected": null, "verified": false, "blue": false, "blueType": null, "descriptionLinks": [], "_type": "snscrape.modules.twitter.User"}, "lang": "en", "rawContent": "how do i post my titties on my timeline without being a whore", "replyCount": 3, "retweetCount": 2, "likeCount": 15, "quoteCount": 0, "conversationId": 1663683269299408896, "conversationIdStr": "1663683269299408896", "hashtags": [], "cashtags": [], "mentionedUsers": [], "links": [], "viewCount": 1486, "retweetedTweet": null, "quotedTweet": null, "place": {"id": "981989c5b11d5119", "fullName": "Visalia, CA", "name": "Visalia", "type": "city", "country": "United States", "countryCode": "US"}, "coordinates": null, "inReplyToTweetId": null, "inReplyToTweetIdStr": null, "inReplyToUser": null, "source": "<a href=\"http://twitter.com/download/iphone\" rel=\"nofollow\">Twitter for iPhone</a>", "sourceUrl": "http://twitter.com/download/iphone", "sourceLabel": "Twitter for iPhone", "media": {"photos": [], "videos": [], "animated": []}, "_type": "snscrape.modules.twitter.Tweet"},
{"id": 1663682440714682368, "id_str": "1663682440714682368", "url": "https://twitter.com/Saqib_hmed/status/1663682440714682368", "date": "2023-05-30 23:02:58+00:00", "user": {"id": 1936314631, "id_str": "1936314631", "url": "https://twitter.com/Saqib_hmed", "username": "Saqib_hmed", "displayname": "Saqib Ahmed", "rawDescription": "I often struggle to reconcile my nerdy side with my ratchet side - Sometimes I pen my thoughts -https://t.co/EP0Tfw3eE4 - Obstreperous- Vicit qui se vincit", "created": "2013-10-05 03:32:16+00:00", "followersCount": 3262, "friendsCount": 305, "statusesCount": 22417, "favouritesCount": 26659, "listedCount": 26, "mediaCount": 5421, "location": "", "profileImageUrl": "https://pbs.twimg.com/profile_images/1703909592881913856/6SpKdHo7_normal.jpg", "profileBannerUrl": "https://pbs.twimg.com/profile_banners/1936314631/1708929488", "protected": null, "verified": false, "blue": true, "blueType": null, "descriptionLinks": [{"url": "https://medium.com/@thnkbiig", "text": "medium.com/@thnkbiig", "tcourl": "https://t.co/EP0Tfw3eE4"}, {"url": "https://linktr.ee/saqib_hmed", "text": "linktr.ee/saqib_hmed", "tcourl": "https://t.co/rJ2b6X8dRU"}], "_type": "snscrape.modules.twitter.User"}, "lang": "en", "rawContent": "Lol I guess donations are slowing down again..\"opportunistic harlot\"..nobody simps for Meghan like Bouzy...nobody LMAO https://t.co/xz0XfnXUTa", "replyCount": 2, "retweetCount": 3, "likeCount": 27, "quoteCount": 0, "conversationId": 1663682440714682368, "conversationIdStr": "1663682440714682368", "hashtags": [], "cashtags": [], "mentionedUsers": [], "links": [], "viewCount": 726, "retweetedTweet": null, "quotedTweet": null, "place": null, "coordinates": null, "inReplyToTweetId": null, "inReplyToTweetIdStr": null, "inReplyToUser": null, "source": "<a href=\"http://twitter.com/download/android\" rel=\"nofollow\">Twitter for Android</a>", "sourceUrl": "http://twitter.com/download/android", "sourceLabel": "Twitter for Android", "media": {"photos": [{"url": "https://pbs.twimg.com/media/FxaWRCZaMAI-kLv.jpg"}], "videos": [], "animated": []}, "_type": "snscrape.modules.twitter.Tweet"},
{"id": 1663682376357093376, "id_str": "1663682376357093376", "url": "https://twitter.com/mad_harlot/status/1663682376357093376", "date": "2023-05-30 23:02:42+00:00", "user": {"id": 879756332609531904, "id_str": "879756332609531904", "url": "https://twitter.com/mad_harlot", "username": "mad_harlot", "displayname": "The Mad Harlot", "rawDescription": "I am Ms. Penelope Proper, a dangerously delicious confection. the naughty Mary Poppins of tea , #teatrixoflongisland #hotwife #enm", "created": "2017-06-27 17:40:29+00:00", "followersCount": 14619, "friendsCount": 14183, "statusesCount": 23469, "favouritesCount": 37223, "listedCount": 37, "mediaCount": 7106, "location": "East Northport, NY", "profileImageUrl": "https://pbs.twimg.com/profile_images/879758369615228932/YbmVhEwO_normal.jpg", "profileBannerUrl": "https://pbs.twimg.com/profile_banners/879756332609531904/1498585804", "protected": null, "verified": false, "blue": false, "blueType": null, "descriptionLinks": [], "_type": "snscrape.modules.twitter.User"}, "lang": "en", "rawContent": "There I am putting a big piece of meat in my mouth https://t.co/WGePFhlXUx", "replyCount": 3, "retweetCount": 5, "likeCount": 74, "quoteCount": 0, "conversationId": 1663682376357093376, "conversationIdStr": "1663682376357093376", "hashtags": [], "cashtags": [], "mentionedUsers": [], "links": [], "viewCount": 2184, "retweetedTweet": null, "quotedTweet": null, "place": null, "coordinates": null, "inReplyToTweetId": null, "inReplyToTweetIdStr": null, "inReplyToUser": null, "source": "<a href=\"http://twitter.com/download/iphone\" rel=\"nofollow\">Twitter for iPhone</a>", "sourceUrl": "http://twitter.com/download/iphone", "sourceLabel": "Twitter for iPhone", "media": {"photos": [{"url": "https://pbs.twimg.com/media/FxaWS-2XoAEbfD1.jpg"}], "videos": [], "animated": []}, "_type": "snscrape.modules.twitter.Tweet"},
{"id": 1663681953504059393, "id_str": "1663681953504059393", "url": "https://twitter.com/ada_lluch/status/1663681953504059393", "date": "2023-05-30 23:01:02+00:00", "user": {"id": 775104300452311041, "id_str": "775104300452311041", "url": "https://twitter.com/ada_lluch", "username": "ada_lluch", "displayname": "Ada Lluch \ud83c\uddea\ud83c\uddf8", "rawDescription": "I still have faith in humanity, but we need to bring back traditional values. I unapologetically tell hard truths. Born and raised in Spain.", "created": "2016-09-11 22:50:40+00:00", "followersCount": 196795, "friendsCount": 674, "statusesCount": 6698, "favouritesCount": 33754, "listedCount": 512, "mediaCount": 758, "location": "", "profileImageUrl": "https://pbs.twimg.com/profile_images/1754172320183201792/ZoM66JDw_normal.jpg", "profileBannerUrl": "https://pbs.twimg.com/profile_banners/775104300452311041/1707062258", "protected": null, "verified": false, "blue": true, "blueType": null, "descriptionLinks": [{"url": "https://www.instagram.com/ada.lluch", "text": "instagram.com/ada.lluch", "tcourl": "https://t.co/zWUA4EGI7n"}], "_type": "snscrape.modules.twitter.User"}, "lang": "en", "rawContent": "Neither Lavern Cox nor Dylan Mulvaney are women.\n\nClimate change is a scam & Greta is a sold out autistic puppet.\n\nThe pandemic was planned by the globalists & they posioned you with the COVID vaccines.\n\nIf you have OnlyFans you are a whore seeking for validation & you are embarrassing your family.\n\nHaving a high body count makes women LOSE their value.\n\nYou are not fat because of genetics, you are just a lazy person who overeats too much. Get fit. \n\nHard truths. Someone has to tell them. \n\nGood night. God bless you.\u2665\ufe0f", "replyCount": 430, "retweetCount": 930, "likeCount": 6881, "quoteCount": 60, "conversationId": 1663681953504059393, "conversationIdStr": "1663681953504059393", "hashtags": [], "cashtags": [], "mentionedUsers": [], "links": [], "viewCount": 329167, "retweetedTweet": null, "quotedTweet": null, "place": null, "coordinates": null, "inReplyToTweetId": null, "inReplyToTweetIdStr": null, "inReplyToUser": null, "source": "<a href=\"http://twitter.com/download/iphone\" rel=\"nofollow\">Twitter for iPhone</a>", "sourceUrl": "http://twitter.com/download/iphone", "sourceLabel": "Twitter for iPhone", "media": {"photos": [], "videos": [], "animated": []}, "_type": "snscrape.modules.twitter.Tweet"},
{"id": 1663681941693169664, "id_str": "1663681941693169664", "url": "https://twitter.com/italianointerno/status/1663681941693169664", "date": "2023-05-30 23:00:59+00:00", "user": {"id": 847986211658584065, "id_str": "847986211658584065", "url": "https://twitter.com/italianointerno", "username": "italianointerno", "displayname": "cat", "rawDescription": "thoughts I only feel confident posting at 1am blazed asf :) e n j o y (: \ud83d\udc99 sapph \ud83d\udc1f", "created": "2017-04-01 01:37:22+00:00", "followersCount": 49, "friendsCount": 181, "statusesCount": 1707, "favouritesCount": 5499, "listedCount": 0, "mediaCount": 129, "location": "Somewhere In Ireland", "profileImageUrl": "https://pbs.twimg.com/profile_images/1352899004611272710/ffhx3bt__normal.jpg", "profileBannerUrl": "https://pbs.twimg.com/profile_banners/847986211658584065/1611391233", "protected": null, "verified": false, "blue": false, "blueType": null, "descriptionLinks": [], "_type": "snscrape.modules.twitter.User"}, "lang": "en", "rawContent": "@_slutty_spice @Bon3man1 @RaxKingIsDead \u201cwahhhh, my thing that people need to survive (shelter) is worth less now\u201d", "replyCount": 1, "retweetCount": 0, "likeCount": 79, "quoteCount": 0, "conversationId": 1663571836494331904, "conversationIdStr": "1663571836494331904", "hashtags": [], "cashtags": [], "mentionedUsers": [{"id": 4123466128, "id_str": "4123466128", "username": "_slutty_spice", "displayname": "\ud835\udd16\ud835\udd29\ud835\udd32\ud835\udd31\ud835\udd31\ud835\udd36 \ud835\udd16\ud835\udd2d\ud835\udd26\ud835\udd20\ud835\udd22", "_type": "snscrape.modules.twitter.UserRef"}, {"id": 1316786474776489985, "id_str": "1316786474776489985", "username": "Bon3man1", "displayname": "Bon3man", "_type": "snscrape.modules.twitter.UserRef"}, {"id": 2254014308, "id_str": "2254014308", "username": "RaxKingIsDead", "displayname": "rax \u2018leads with her crotch\u2019 king", "_type": "snscrape.modules.twitter.UserRef"}], "links": [], "viewCount": 1589, "retweetedTweet": null, "quotedTweet": null, "place": null, "coordinates": null, "inReplyToTweetId": 1663675369604497409, "inReplyToTweetIdStr": "1663675369604497409", "inReplyToUser": {"id": 4123466128, "id_str": "4123466128", "username": "_slutty_spice", "displayname": "\ud835\udd16\ud835\udd29\ud835\udd32\ud835\udd31\ud835\udd31\ud835\udd36 \ud835\udd16\ud835\udd2d\ud835\udd26\ud835\udd20\ud835\udd22", "_type": "snscrape.modules.twitter.UserRef"}, "source": "<a href=\"http://twitter.com/download/iphone\" rel=\"nofollow\">Twitter for iPhone</a>", "sourceUrl": "http://twitter.com/download/iphone", "sourceLabel": "Twitter for iPhone", "media": {"photos": [], "videos": [], "animated": []}, "_type": "snscrape.modules.twitter.Tweet"},
{"id": 1663681930498387969, "id_str": "1663681930498387969", "url": "https://twitter.com/ReggLB/status/1663681930498387969", "date": "2023-05-30 23:00:56+00:00", "user": {"id": 1104928916886687744, "id_str": "1104928916886687744", "url": "https://twitter.com/ReggLB", "username": "ReggLB", "displayname": "Regg", "rawDescription": "", "created": "2019-03-11 02:15:57+00:00", "followersCount": 822, "friendsCount": 513, "statusesCount": 4468, "favouritesCount": 6492, "listedCount": 0, "mediaCount": 236, "location": "", "profileImageUrl": "https://pbs.twimg.com/profile_images/1706131905995853825/vGarIBgg_normal.jpg", "profileBannerUrl": "https://pbs.twimg.com/profile_banners/1104928916886687744/1708912894", "protected": null, "verified": false, "blue": false, "blueType": null, "descriptionLinks": [], "_type": "snscrape.modules.twitter.User"}, "lang": "en", "rawContent": "if my hoe go to a block party that ain\u2019t my hoe at all no discussion", "replyCount": 9, "retweetCount": 26, "likeCount": 62, "quoteCount": 5, "conversationId": 1663681930498387969, "conversationIdStr": "1663681930498387969", "hashtags": [], "cashtags": [], "mentionedUsers": [], "links": [], "viewCount": 23340, "retweetedTweet": null, "quotedTweet": null, "place": null, "coordinates": null, "inReplyToTweetId": null, "inReplyToTweetIdStr": null, "inReplyToUser": null, "source": "<a href=\"http://twitter.com/download/iphone\" rel=\"nofollow\">Twitter for iPhone</a>", "sourceUrl": "http://twitter.com/download/iphone", "sourceLabel": "Twitter for iPhone", "media": {"photos": [], "videos": [], "animated": []}, "_type": "snscrape.modules.twitter.Tweet"},
{"id": 1663681872767877120, "id_str": "1663681872767877120", "url": "https://twitter.com/Graysonwayne95/status/1663681872767877120", "date": "2023-05-30 23:00:42+00:00", "user": {"id": 1112730438, "id_str": "1112730438", "url": "https://twitter.com/Graysonwayne95", "username": "Graysonwayne95", "displayname": "\ud83d\uddfdK \ud83c\udfaa", "rawDescription": "Deep roots are not reached by the frost \u272d", "created": "2013-01-22 21:58:53+00:00", "followersCount": 1909, "friendsCount": 652, "statusesCount": 53975, "favouritesCount": 134631, "listedCount": 6, "mediaCount": 5912, "location": "Texas, USA", "profileImageUrl": "https://pbs.twimg.com/profile_images/1752166180847050752/ZNyxiLGe_normal.jpg", "profileBannerUrl": "https://pbs.twimg.com/profile_banners/1112730438/1702248316", "protected": null, "verified": false, "blue": false, "blueType": null, "descriptionLinks": [{"url": "http://instagram.com/obama", "text": "instagram.com/obama", "tcourl": "https://t.co/WUyZndmvyG"}], "_type": "snscrape.modules.twitter.User"}, "lang": "en", "rawContent": "Dressed like a whore (5in seem shorts and polo)", "replyCount": 2, "retweetCount": 0, "likeCount": 16, "quoteCount": 0, "conversationId": 1663681872767877120, "conversationIdStr": "1663681872767877120", "hashtags": [], "cashtags": [], "mentionedUsers": [], "links": [], "viewCount": 446, "retweetedTweet": null, "quotedTweet": null, "place": null, "coordinates": null, "inReplyToTweetId": null, "inReplyToTweetIdStr": null, "inReplyToUser": null, "source": "<a href=\"http://twitter.com/download/iphone\" rel=\"nofollow\">Twitter for iPhone</a>", "sourceUrl": "http://twitter.com/download/iphone", "sourceLabel": "Twitter for iPhone", "media": {"photos": [], "videos": [], "animated": []}, "_type": "snscrape.modules.twitter.Tweet"},
{"id": 1663681823635849217, "id_str": "1663681823635849217", "url": "https://twitter.com/chemonee/status/1663681823635849217", "date": "2023-05-30 23:00:31+00:00", "user": {"id": 1064210435589767169, "id_str": "1064210435589767169", "url": "https://twitter.com/chemonee", "username": "chemonee", "displayname": "ch\u0117 monee", "rawDescription": "\ud83e\udd8b.", "created": "2018-11-18 17:35:14+00:00", "followersCount": 14427, "friendsCount": 249, "statusesCount": 8259, "favouritesCount": 6001, "listedCount": 4, "mediaCount": 72, "location": "", "profileImageUrl": "https://pbs.twimg.com/profile_images/1723917161238757376/hORZ2okx_normal.jpg", "profileBannerUrl": "https://pbs.twimg.com/profile_banners/1064210435589767169/1701833828", "protected": null, "verified": false, "blue": false, "blueType": null, "descriptionLinks": [{"url": "https://youtube.com/@chemonee?si=hbewxxCUtqJ5perR", "text": "youtube.com/@chemonee?si=h\u2026", "tcourl": "https://t.co/WjYuP47NCP"}], "_type": "snscrape.modules.twitter.User"}, "lang": "en", "rawContent": "I\u2019ll take my hoe back just to cause some commotion.", "replyCount": 7, "retweetCount": 501, "likeCount": 1291, "quoteCount": 174, "conversationId": 1663681823635849217, "conversationIdStr": "1663681823635849217", "hashtags": [], "cashtags": [], "mentionedUsers": [], "links": [], "viewCount": 138854, "retweetedTweet": null, "quotedTweet": null, "place": null, "coordinates": null, "inReplyToTweetId": null, "inReplyToTweetIdStr": null, "inReplyToUser": null, "source": "<a href=\"http://twitter.com/download/iphone\" rel=\"nofollow\">Twitter for iPhone</a>", "sourceUrl": "http://twitter.com/download/iphone", "sourceLabel": "Twitter for iPhone", "media": {"photos": [], "videos": [], "animated": []}, "_type": "snscrape.modules.twitter.Tweet"},
{"id": 1663681727548755969, "id_str": "1663681727548755969", "url": "https://twitter.com/PuritanMines/status/1663681727548755969", "date": "2023-05-30 23:00:08+00:00", "user": {"id": 1351558047399727106, "id_str": "1351558047399727106", "url": "https://twitter.com/PuritanMines", "username": "PuritanMines", "displayname": "Puritan Gold", "rawDescription": "\u201cIn an era of theological confusion and moral compromise, we can gain much by reading the Puritans.\u201d \u2014Joel Beeke | Admin: @alfredsparks", "created": "2021-01-19 15:52:14+00:00", "followersCount": 12768, "friendsCount": 32, "statusesCount": 3308, "favouritesCount": 2646, "listedCount": 74, "mediaCount": 86, "location": "", "profileImageUrl": "https://pbs.twimg.com/profile_images/1401891703741505539/dWLIKlom_normal.jpg", "profileBannerUrl": "https://pbs.twimg.com/profile_banners/1351558047399727106/1622989820", "protected": null, "verified": false, "blue": false, "blueType": null, "descriptionLinks": [], "_type": "snscrape.modules.twitter.User"}, "lang": "en", "rawContent": "Where hatred of sin is, there will be a killing of sin, but if you let it live, you hate not sin.\n\n\u2014Thomas Hooker, Self-Denial, Pg. 69", "replyCount": 1, "retweetCount": 30, "likeCount": 114, "quoteCount": 1, "conversationId": 1663681727548755969, "conversationIdStr": "1663681727548755969", "hashtags": [], "cashtags": [], "mentionedUsers": [], "links": [], "viewCount": 4540, "retweetedTweet": null, "quotedTweet": null, "place": null, "coordinates": null, "inReplyToTweetId": null, "inReplyToTweetIdStr": null, "inReplyToUser": null, "source": "<a href=\"http://twitter.com/download/iphone\" rel=\"nofollow\">Twitter for iPhone</a>", "sourceUrl": "http://twitter.com/download/iphone", "sourceLabel": "Twitter for iPhone", "media": {"photos": [], "videos": [], "animated": []}, "_type": "snscrape.modules.twitter.Tweet"},
{"id": 1663681319480483842, "id_str": "1663681319480483842", "url": "https://twitter.com/Nicktyde/status/1663681319480483842", "date": "2023-05-30 22:58:30+00:00", "user": {"id": 3196448860, "id_str": "3196448860", "url": "https://twitter.com/Nicktyde", "username": "Nicktyde", "displayname": "Nick", "rawDescription": "Unhinged, Unwell, and Unmedicated (babygirl) (he/him) 18+", "created": "2015-04-23 00:29:33+00:00", "followersCount": 7752, "friendsCount": 5347, "statusesCount": 27837, "favouritesCount": 160560, "listedCount": 2, "mediaCount": 4789, "location": "Shavertown, PA", "profileImageUrl": "https://pbs.twimg.com/profile_images/1757088627476074496/UmZphxYv_normal.jpg", "profileBannerUrl": "https://pbs.twimg.com/profile_banners/3196448860/1705620214", "protected": null, "verified": false, "blue": false, "blueType": null, "descriptionLinks": [{"url": "http://Instagram.com/nicktyde", "text": "Instagram.com/nicktyde", "tcourl": "https://t.co/9aP7kSk8C1"}], "_type": "snscrape.modules.twitter.User"}, "lang": "en", "rawContent": "I\u2019m a slut for promotional ice cream https://t.co/Vi9RRXbs2L", "replyCount": 9, "retweetCount": 1, "likeCount": 104, "quoteCount": 0, "conversationId": 1663681319480483842, "conversationIdStr": "1663681319480483842", "hashtags": [], "cashtags": [], "mentionedUsers": [], "links": [], "viewCount": 1534, "retweetedTweet": null, "quotedTweet": null, "place": null, "coordinates": null, "inReplyToTweetId": null, "inReplyToTweetIdStr": null, "inReplyToUser": null, "source": "<a href=\"http://twitter.com/download/iphone\" rel=\"nofollow\">Twitter for iPhone</a>", "sourceUrl": "http://twitter.com/download/iphone", "sourceLabel": "Twitter for iPhone", "media": {"photos": [{"url": "https://pbs.twimg.com/media/FxaVV2jWYAA2Szt.jpg"}], "videos": [], "animated": []}, "_type": "snscrape.modules.twitter.Tweet"},
{"id": 1663680455634296838, "id_str": "1663680455634296838", "url": "https://twitter.com/queenserena252/status/1663680455634296838", "date": "2023-05-30 22:55:04+00:00", "user": {"id": 1217984000402370564, "id_str": "1217984000402370564", "url": "https://twitter.com/queenserena252", "username": "queenserena252", "displayname": "#FREETORYLANEZ", "rawDescription": "This page is dedicated to the Greatest Athlete of all times.\u2014The Queen of modern women\u2019s tennis, Serena Jameka Williams. | #TeamSerena #RenasArmy", "created": "2020-01-17 01:36:37+00:00", "followersCount": 552, "friendsCount": 324, "statusesCount": 17350, "favouritesCount": 696, "listedCount": 2, "mediaCount": 469, "location": "", "profileImageUrl": "https://pbs.twimg.com/profile_images/1230535845360234497/HlkDUkp6_normal.jpg", "profileBannerUrl": "https://pbs.twimg.com/profile_banners/1217984000402370564/1660105894", "protected": null, "verified": false, "blue": false, "blueType": null, "descriptionLinks": [], "_type": "snscrape.modules.twitter.User"}, "lang": "en", "rawContent": "Yooooooo I\u2019m \ud83d\udc80 \ud83e\udd23 @ da way they clowning that whore for her body count! \ud83d\udc0e\ud83d\udca9\ud83c\udf1a\ud83e\udd76", "replyCount": 5, "retweetCount": 5, "likeCount": 33, "quoteCount": 1, "conversationId": 1663680455634296838, "conversationIdStr": "1663680455634296838", "hashtags": [], "cashtags": [], "mentionedUsers": [], "links": [], "viewCount": 1357, "retweetedTweet": null, "quotedTweet": null, "place": null, "coordinates": null, "inReplyToTweetId": null, "inReplyToTweetIdStr": null, "inReplyToUser": null, "source": "<a href=\"http://twitter.com/download/iphone\" rel=\"nofollow\">Twitter for iPhone</a>", "sourceUrl": "http://twitter.com/download/iphone", "sourceLabel": "Twitter for iPhone", "media": {"photos": [], "videos": [], "animated": []}, "_type": "snscrape.modules.twitter.Tweet"},
{"id": 1663680408188342272, "id_str": "1663680408188342272", "url": "https://twitter.com/gesmjj/status/1663680408188342272", "date": "2023-05-30 22:54:53+00:00", "user": {"id": 712666933167067136, "id_str": "712666933167067136", "url": "https://twitter.com/gesmjj", "username": "gesmjj", "displayname": "gesel", "rawDescription": "professional shit talker", "created": "2016-03-23 15:46:52+00:00", "followersCount": 6146, "friendsCount": 948, "statusesCount": 8859, "favouritesCount": 10440, "listedCount": 8, "mediaCount": 128, "location": "", "profileImageUrl": "https://pbs.twimg.com/profile_images/1765132744814710785/SktLH9Am_normal.jpg", "profileBannerUrl": "https://pbs.twimg.com/profile_banners/712666933167067136/1644612800", "protected": null, "verified": false, "blue": false, "blueType": null, "descriptionLinks": [{"url": "http://instagram.com/gesmjj", "text": "instagram.com/gesmjj", "tcourl": "https://t.co/LkqqZCFoSR"}], "_type": "snscrape.modules.twitter.User"}, "lang": "en", "rawContent": "Im a lover girl stuck in a hoe ass generation", "replyCount": 0, "retweetCount": 10, "likeCount": 33, "quoteCount": 2, "conversationId": 1663680408188342272, "conversationIdStr": "1663680408188342272", "hashtags": [], "cashtags": [], "mentionedUsers": [], "links": [], "viewCount": 8145, "retweetedTweet": null, "quotedTweet": null, "place": null, "coordinates": null, "inReplyToTweetId": null, "inReplyToTweetIdStr": null, "inReplyToUser": null, "source": "<a href=\"http://twitter.com/download/iphone\" rel=\"nofollow\">Twitter for iPhone</a>", "sourceUrl": "http://twitter.com/download/iphone", "sourceLabel": "Twitter for iPhone", "media": {"photos": [], "videos": [], "animated": []}, "_type": "snscrape.modules.twitter.Tweet"},
{"id": 1663679548603654144, "id_str": "1663679548603654144", "url": "https://twitter.com/teerasvp/status/1663679548603654144", "date": "2023-05-30 22:51:28+00:00", "user": {"id": 1339000135813005312, "id_str": "1339000135813005312", "url": "https://twitter.com/teerasvp", "username": "teerasvp", "displayname": "paige \ud81a\uddb9 APRIL 10", "rawDescription": "diagnosed with sawtism \u269d sixteen \u269d australian \u269d tiktok&insta: teerasvp \u269d backup: @bjrgvnrns", "created": "2020-12-16 00:11:42+00:00", "followersCount": 715, "friendsCount": 621, "statusesCount": 3363, "favouritesCount": 73231, "listedCount": 8, "mediaCount": 1103, "location": "any prns ", "profileImageUrl": "https://pbs.twimg.com/profile_images/1762084148859359232/r36hpphw_normal.jpg", "profileBannerUrl": "https://pbs.twimg.com/profile_banners/1339000135813005312/1708948584", "protected": null, "verified": false, "blue": false, "blueType": null, "descriptionLinks": [{"url": "https://chvcky.carrd.co/", "text": "chvcky.carrd.co", "tcourl": "https://t.co/KhltrzH8UZ"}], "_type": "snscrape.modules.twitter.User"}, "lang": "en", "rawContent": "wheres that i am become a whore image https://t.co/vVFTKgt3v9", "replyCount": 1, "retweetCount": 7, "likeCount": 63, "quoteCount": 0, "conversationId": 1663679548603654144, "conversationIdStr": "1663679548603654144", "hashtags": [], "cashtags": [], "mentionedUsers": [], "links": [], "viewCount": 1180, "retweetedTweet": null, "quotedTweet": null, "place": null, "coordinates": null, "inReplyToTweetId": null, "inReplyToTweetIdStr": null, "inReplyToUser": null, "source": "<a href=\"http://twitter.com/download/iphone\" rel=\"nofollow\">Twitter for iPhone</a>", "sourceUrl": "http://twitter.com/download/iphone", "sourceLabel": "Twitter for iPhone", "media": {"photos": [{"url": "https://pbs.twimg.com/media/FxaTusHakAALuv8.jpg"}], "videos": [], "animated": []}, "_type": "snscrape.modules.twitter.Tweet"},
{"id": 1663677040594149377, "id_str": "1663677040594149377", "url": "https://twitter.com/TimsDatDude/status/1663677040594149377", "date": "2023-05-30 22:41:30+00:00", "user": {"id": 365714696, "id_str": "365714696", "url": "https://twitter.com/TimsDatDude", "username": "TimsDatDude", "displayname": "FloridaMan", "rawDescription": "| Poet | The U | #LYMYA \ud83d\udc7c\ud83c\udffd", "created": "2011-08-31 22:12:08+00:00", "followersCount": 3544, "friendsCount": 807, "statusesCount": 160337, "favouritesCount": 9645, "listedCount": 9, "mediaCount": 9554, "location": "Miami-Orlando ", "profileImageUrl": "https://pbs.twimg.com/profile_images/1743099311070547968/vE7XMxMe_normal.jpg", "profileBannerUrl": "https://pbs.twimg.com/profile_banners/365714696/1708063669", "protected": null, "verified": false, "blue": false, "blueType": null, "descriptionLinks": [], "_type": "snscrape.modules.twitter.User"}, "lang": "en", "rawContent": "Jus bought some 5\u201d shorts. 4 different colors &amp; styles. Summer is here, time to slut", "replyCount": 4, "retweetCount": 2, "likeCount": 9, "quoteCount": 8, "conversationId": 1663677040594149377, "conversationIdStr": "1663677040594149377", "hashtags": [], "cashtags": [], "mentionedUsers": [], "links": [], "viewCount": 5991, "retweetedTweet": null, "quotedTweet": null, "place": null, "coordinates": null, "inReplyToTweetId": null, "inReplyToTweetIdStr": null, "inReplyToUser": null, "source": "<a href=\"http://twitter.com/download/iphone\" rel=\"nofollow\">Twitter for iPhone</a>", "sourceUrl": "http://twitter.com/download/iphone", "sourceLabel": "Twitter for iPhone", "media": {"photos": [], "videos": [], "animated": []}, "_type": "snscrape.modules.twitter.Tweet"},
{"id": 1663676388396929025, "id_str": "1663676388396929025", "url": "https://twitter.com/yangteolz/status/1663676388396929025", "date": "2023-05-30 22:38:55+00:00", "user": {"id": 1409194793222111232, "id_str": "1409194793222111232", "url": "https://twitter.com/yangteolz", "username": "yangteolz", "displayname": "\ud83d\udc08", "rawDescription": "gunwook fans weishenville", "created": "2021-06-27 17:00:06+00:00", "followersCount": 2441, "friendsCount": 1426, "statusesCount": 61728, "favouritesCount": 45386, "listedCount": 49, "mediaCount": 14658, "location": "she they", "profileImageUrl": "https://pbs.twimg.com/profile_images/1765015913198501888/hJoP3Y--_normal.jpg", "profileBannerUrl": "https://pbs.twimg.com/profile_banners/1409194793222111232/1709647430", "protected": null, "verified": false, "blue": false, "blueType": null, "descriptionLinks": [{"url": "http://allforlove.carrd.co", "text": "allforlove.carrd.co", "tcourl": "https://t.co/SZAN8elLw1"}], "_type": "snscrape.modules.twitter.User"}, "lang": "en", "rawContent": "desperately need u guys to realise this isnt a \"which is the better song\" poll its litrly \"which is the better hoe anthem\" poll and love talk is CLEARING????", "replyCount": 3, "retweetCount": 4, "likeCount": 65, "quoteCount": 0, "conversationId": 1663676388396929025, "conversationIdStr": "1663676388396929025", "hashtags": [], "cashtags": [], "mentionedUsers": [], "links": [], "viewCount": 2881, "retweetedTweet": null, "quotedTweet": null, "place": null, "coordinates": null, "inReplyToTweetId": null, "inReplyToTweetIdStr": null, "inReplyToUser": null, "source": "<a href=\"http://twitter.com/download/iphone\" rel=\"nofollow\">Twitter for iPhone</a>", "sourceUrl": "http://twitter.com/download/iphone", "sourceLabel": "Twitter for iPhone", "media": {"photos": [], "videos": [], "animated": []}, "_type": "snscrape.modules.twitter.Tweet"},
{"id": 1663676339252068352, "id_str": "1663676339252068352", "url": "https://twitter.com/Bon3man1/status/1663676339252068352", "date": "2023-05-30 22:38:43+00:00", "user": {"id": 1316786474776489985, "id_str": "1316786474776489985", "url": "https://twitter.com/Bon3man1", "username": "Bon3man1", "displayname": "Bon3man", "rawDescription": "just found the remove follower button", "created": "2020-10-15 17:02:28+00:00", "followersCount": 0, "friendsCount": 258, "statusesCount": 11351, "favouritesCount": 57469, "listedCount": 0, "mediaCount": 251, "location": "fuck xenoblade", "profileImageUrl": "https://pbs.twimg.com/profile_images/1316787001698512897/TbqDJYsf_normal.jpg", "profileBannerUrl": "https://pbs.twimg.com/profile_banners/1316786474776489985/1603114071", "protected": null, "verified": false, "blue": false, "blueType": null, "descriptionLinks": [], "_type": "snscrape.modules.twitter.User"}, "lang": "en", "rawContent": "@_slutty_spice @RaxKingIsDead if i said i didn\u2019t like your outfit would you go home and change it", "replyCount": 1, "retweetCount": 0, "likeCount": 78, "quoteCount": 0, "conversationId": 1663571836494331904, "conversationIdStr": "1663571836494331904", "hashtags": [], "cashtags": [], "mentionedUsers": [{"id": 4123466128, "id_str": "4123466128", "username": "_slutty_spice", "displayname": "\ud835\udd16\ud835\udd29\ud835\udd32\ud835\udd31\ud835\udd31\ud835\udd36 \ud835\udd16\ud835\udd2d\ud835\udd26\ud835\udd20\ud835\udd22", "_type": "snscrape.modules.twitter.UserRef"}, {"id": 2254014308, "id_str": "2254014308", "username": "RaxKingIsDead", "displayname": "rax \u2018leads with her crotch\u2019 king", "_type": "snscrape.modules.twitter.UserRef"}], "links": [], "viewCount": 651, "retweetedTweet": null, "quotedTweet": null, "place": null, "coordinates": null, "inReplyToTweetId": 1663675369604497409, "inReplyToTweetIdStr": "1663675369604497409", "inReplyToUser": {"id": 4123466128, "id_str": "4123466128", "username": "_slutty_spice", "displayname": "\ud835\udd16\ud835\udd29\ud835\udd32\ud835\udd31\ud835\udd31\ud835\udd36 \ud835\udd16\ud835\udd2d\ud835\udd26\ud835\udd20\ud835\udd22", "_type": "snscrape.modules.twitter.UserRef"}, "source": "<a href=\"http://twitter.com/download/iphone\" rel=\"nofollow\">Twitter for iPhone</a>", "sourceUrl": "http://twitter.com/download/iphone", "sourceLabel": "Twitter for iPhone", "media": {"photos": [], "videos": [], "animated": []}, "_type": "snscrape.modules.twitter.Tweet"},
{"id": 1663676118665408515, "id_str": "1663676118665408515", "url": "https://twitter.com/leafsnlifts/status/1663676118665408515", "date": "2023-05-30 22:37:50+00:00", "user": {"id": 1605665595604754442, "id_str": "1605665595604754442", "url": "https://twitter.com/leafsnlifts", "username": "leafsnlifts", "displayname": "leggo my meggo\ud83e\udd8b", "rawDescription": "A suffering Leafs fan, and a suffering gym goer. Big thighs, bigger heart :)", "created": "2022-12-21 20:45:16+00:00", "followersCount": 7425, "friendsCount": 518, "statusesCount": 8667, "favouritesCount": 13232, "listedCount": 11, "mediaCount": 608, "location": "Downtown, Canada", "profileImageUrl": "https://pbs.twimg.com/profile_images/1759669989303300096/2IWTPhRv_normal.jpg", "profileBannerUrl": "https://pbs.twimg.com/profile_banners/1605665595604754442/1707092133", "protected": null, "verified": false, "blue": false, "blueType": null, "descriptionLinks": [], "_type": "snscrape.modules.twitter.User"}, "lang": "en", "rawContent": "Wearing my \u201clift heavy, be slutty\u201d shirt and i\u2019m like 99% certain it is giving me extra strength and extra life", "replyCount": 0, "retweetCount": 0, "likeCount": 28, "quoteCount": 0, "conversationId": 1663676118665408515, "conversationIdStr": "1663676118665408515", "hashtags": [], "cashtags": [], "mentionedUsers": [], "links": [], "viewCount": 1849, "retweetedTweet": null, "quotedTweet": null, "place": null, "coordinates": null, "inReplyToTweetId": null, "inReplyToTweetIdStr": null, "inReplyToUser": null, "source": "<a href=\"http://twitter.com/download/iphone\" rel=\"nofollow\">Twitter for iPhone</a>", "sourceUrl": "http://twitter.com/download/iphone", "sourceLabel": "Twitter for iPhone", "media": {"photos": [], "videos": [], "animated": []}, "_type": "snscrape.modules.twitter.Tweet"}
]